comic_matcher/__init__.py
comic_matcher/cli.py
comic_matcher/matcher.py
comic_matcher/parser.py
comic_matcher/team_up_matcher.py
comic_matcher/utils.py
comic_matcher/versus_matcher.py
tests/__init__.py
tests/conftest.py
tests/conftest_fixtures.py
tests/test_bad_matches.py
tests/test_bad_matches_edge_cases.py
tests/test_bad_matches_integration.py
tests/test_cli.py
tests/test_compound_titles.py
tests/test_full_marvel_shadows.py
tests/test_marvel_direct.py
tests/test_marvel_shadows.py
tests/test_marvel_shadows_fix.py
tests/test_matcher.py
tests/test_minimal.py
tests/test_mismatches_basic.py
tests/test_mismatches_comprehensive.py
tests/test_no_subtitle_approach.py
tests/test_parser.py
tests/test_parser_bad_matches.py
tests/test_sequel_detection.py
tests/test_title_matchers.py
tests/test_title_structural_differences.py
tests/test_utils.py
tests/test_wolverine_titles.py
comic_matcher-0.2.2.dist-info/METADATA
comic_matcher-0.2.2.dist-info/WHEEL
comic_matcher-0.2.2.dist-info/entry_points.txt
comic_matcher-0.2.2.dist-info/top_level.txt
comic_matcher-0.2.2.dist-info/RECORD
